ooverpunch-0.2.0.dist-info/METADATA
ooverpunch-0.2.0.dist-info/WHEEL
ooverpunch-0.2.0.dist-info/licenses/LICENSE
ooverpunch.libs/libgcc_s-b5472b99.so.1
ooverpunch/__init__.py
ooverpunch/ooverpunch.pypy38-pp73-x86-linux-gnu.so
ooverpunch-0.2.0.dist-info/RECORD
