Metadata-Version: 2.3
Name: ooverpunch
Version: 0.2.0
Classifier: Programming Language :: Rust
Classifier: Programming Language :: Python :: Implementation :: CPython
Classifier: Programming Language :: Python :: Implementation :: PyPy
License-File: LICENSE
Home-Page: https://github.com/f0rk/ooverpunch
Requires-Python: >=3.8
